setup.py
crispys_webkit/__init__.py
crispys_webkit/exceptions.py
crispys_webkit/objextend.py
crispys_webkit/objprope.py
crispys_webkit/objverify.py
crispys_webkit/tests.py
crispys_webkit/urls.py
crispys_webkit.egg-info/PKG-INFO
crispys_webkit.egg-info/SOURCES.txt
crispys_webkit.egg-info/dependency_links.txt
crispys_webkit.egg-info/not-zip-safe
crispys_webkit.egg-info/requires.txt
crispys_webkit.egg-info/top_level.txt