Metadata-Version: 1.0
Name: crispys-webkit
Version: 0.1.141
Summary: Some common web functionalites that I use.
Home-page: http://github.com/crispycret/crispys_webkit
Author: Brandon Nadeau
Author-email: brandonmnadeau@hotmail.com
License: MIT
Platform: UNKNOWN
